LICENSE
README.md
setup.py
dataclass_tree/__init__.py
dataclass_tree/tree.py
dataclass_tree.egg-info/PKG-INFO
dataclass_tree.egg-info/SOURCES.txt
dataclass_tree.egg-info/dependency_links.txt
dataclass_tree.egg-info/not-zip-safe
dataclass_tree.egg-info/top_level.txt
test/test_tree.py