Metadata-Version: 2.4
Name: dataclass-tree
Version: 0.5.0
Summary: Generic tree dataclass with visitor
Home-page: https://varkenvarken.github.io/dataclass-tree/
Author: varkenvarken
Author-email: test@example.com
License: GPLv3
Classifier: Development Status :: 4 - Beta
Classifier: Programming Language :: Python :: 3.11
Classifier: License :: OSI Approved :: GNU General Public License v3 (GPLv3)
Classifier: Operating System :: OS Independent
Requires-Python: >=3.11
License-File: LICENSE
Dynamic: author
Dynamic: author-email
Dynamic: classifier
Dynamic: description
Dynamic: description-content-type
Dynamic: home-page
Dynamic: license
Dynamic: license-file
Dynamic: requires-python
Dynamic: summary
